xyj_database
