Metadata-Version: 2.1
Name: xyj-database
Version: 0.2
Summary: A package for show data
Home-page: UNKNOWN
Author: Yijie Xia
Author-email: yijiexia@pku.edu.cn
License: UNKNOWN
Platform: UNKNOWN
Classifier: Programming Language :: Python :: 3 :: Only
Classifier: Development Status :: 4 - Beta
Classifier: Operating System :: OS Independent
Requires-Python: >=3.6
